pipe2prompt/__init__.py
pipe2prompt/cli.py
pipe2prompt/completion.py
pipe2prompt/prompt.py
pipe2prompt/utils.py
pipe2prompt-0.1.1.dist-info/LICENSE.txt
pipe2prompt-0.1.1.dist-info/METADATA
pipe2prompt-0.1.1.dist-info/WHEEL
pipe2prompt-0.1.1.dist-info/entry_points.txt
pipe2prompt-0.1.1.dist-info/top_level.txt
pipe2prompt-0.1.1.dist-info/RECORD
